array_api/_2022_12.py
array_api/_2023_12.py
array_api/_2024_12.py
array_api/__init__.py
array_api/__main__.py
array_api/_draft.py
array_api/main.py
array_api/py.typed
array_api/cli/__init__.py
array_api/cli/_main.py
array_api/cli/cli.py
array_api-1.0.0.dist-info/licenses/LICENSE
array_api-1.0.0.dist-info/licenses/LICENSE-MIT
array_api_compat/__init__.pyi
array_api-1.0.0.dist-info/METADATA
array_api-1.0.0.dist-info/WHEEL
array_api-1.0.0.dist-info/entry_points.txt
array_api-1.0.0.dist-info/top_level.txt
array_api-1.0.0.dist-info/RECORD
