Metadata-Version: 2.4
Name: array-api
Version: 1.0.0
Summary: Typing for array API and array-api-compat
Author-email: 34j <34j.95a2p@simplelogin.com>
License-Expression: MIT AND Apache-2.0
Project-URL: Bug Tracker, https://github.com/34j/array-api/issues
Project-URL: Changelog, https://github.com/34j/array-api/blob/main/CHANGELOG.md
Project-URL: documentation, https://array-api.readthedocs.io
Project-URL: repository, https://github.com/34j/array-api
Classifier: Development Status :: 2 - Pre-Alpha
Classifier: Intended Audience :: Developers
Classifier: Natural Language :: English
Classifier: Operating System :: OS Independent
Classifier: Programming Language :: Python :: 3.9
Classifier: Programming Language :: Python :: 3.10
Classifier: Programming Language :: Python :: 3.11
Classifier: Programming Language :: Python :: 3.12
Classifier: Programming Language :: Python :: 3.13
Classifier: Topic :: Software Development :: Libraries
Requires-Python: >=3.9
License-File: LICENSE
License-File: LICENSE-MIT
Requires-Dist: attrs>=25.3.0
Requires-Dist: rich>=10
Requires-Dist: typer<1,>=0.15
Dynamic: license-file
